antlr3/__init__.py
antlr3/compat.py
antlr3/constants.py
antlr3/debug.py
antlr3/dfa.py
antlr3/dottreegen.py
antlr3/exceptions.py
antlr3/extras.py
antlr3/main.py
antlr3/recognizers.py
antlr3/streams.py
antlr3/tokens.py
antlr3/tree.py
antlr3/treewizard.py
ll/UL4Lexer.py
ll/UL4Parser.py
ll/_ansistyle.cp310-win32.pyd
ll/_misc.cp310-win32.pyd
ll/_xml_codec.cp310-win32.pyd
ll/ansistyle.py
ll/astyle.py
ll/color.py
ll/daemon.py
ll/make.py
ll/misc.py
ll/nightshade.py
ll/pysql.py
ll/sisyphus.py
ll/toxicc.py
ll/ul4c.py
ll/ul4on.py
ll/url.py
ll/xml_codec.py
ll/orasql/__init__.py
ll/orasql/scripts/__init__.py
ll/orasql/scripts/oracreate.py
ll/orasql/scripts/oracycles.py
ll/orasql/scripts/oradelete.py
ll/orasql/scripts/oradiff.py
ll/orasql/scripts/oradrop.py
ll/orasql/scripts/orafind.py
ll/orasql/scripts/oragrant.py
ll/orasql/scripts/oramerge.py
ll/orasql/scripts/orareindex.py
ll/scripts/__init__.py
ll/scripts/rul4.py
ll/scripts/ucat.py
ll/scripts/ucp.py
ll/scripts/udiff.py
ll/scripts/uls.py
ll/xist/__init__.py
ll/xist/css.py
ll/xist/parse.py
ll/xist/present.py
ll/xist/sgmlop.cp310-win32.pyd
ll/xist/sims.py
ll/xist/xfind.py
ll/xist/xnd.py
ll/xist/xsc.py
ll/xist/data/px/spc.gif
ll/xist/ns/__init__.py
ll/xist/ns/abbr.py
ll/xist/ns/atom.py
ll/xist/ns/chars.py
ll/xist/ns/code.py
ll/xist/ns/detox.py
ll/xist/ns/doc.py
ll/xist/ns/docbook.py
ll/xist/ns/fo.py
ll/xist/ns/form.py
ll/xist/ns/html.py
ll/xist/ns/htmlspecials.py
ll/xist/ns/jsp.py
ll/xist/ns/meta.py
ll/xist/ns/metal.py
ll/xist/ns/php.py
ll/xist/ns/rest.py
ll/xist/ns/rng.py
ll/xist/ns/rss091.py
ll/xist/ns/rss20.py
ll/xist/ns/ruby.py
ll/xist/ns/specials.py
ll/xist/ns/struts_config.py
ll/xist/ns/struts_html.py
ll/xist/ns/svg.py
ll/xist/ns/tal.py
ll/xist/ns/tld.py
ll/xist/ns/toxic.py
ll/xist/ns/ul4.py
ll/xist/ns/wml.py
ll/xist/ns/xlink.py
ll/xist/ns/xml.py
ll/xist/scripts/__init__.py
ll/xist/scripts/doc2txt.py
ll/xist/scripts/dtd2xsc.py
ll/xist/scripts/tld2xsc.py
ll/xist/scripts/uhpp.py
ll/xist/scripts/xml2xsc.py
ll_xist-5.80.1.dist-info/METADATA
ll_xist-5.80.1.dist-info/WHEEL
ll_xist-5.80.1.dist-info/entry_points.txt
ll_xist-5.80.1.dist-info/top_level.txt
ll_xist-5.80.1.dist-info/RECORD
