Metadata-Version: 2.1
Name: ll-xist
Version: 5.80.1
Summary: Extensible HTML/XML generator, cross-platform templating language, Oracle utilities and various other tools
Home-page: http://python.livinglogic.de/
Author: Walter Doerwald
Author-email: walter@livinglogic.de
License: MIT
Download-URL: http://python.livinglogic.de/DOWNLOAD.html
Keywords: ANSI,CSS,CherryPy,FTP,HLS,HSB,HSC,HSV,HTML,HTTP,Oracle,PI,PL/SQL,RFC 2396,RGB,SVG,URL,XHTML,XML,XSL-FO,XSLT,build,codec,color,cron,cx_Oracle,decorator,escape sequence,execnet,iterator,job,make,procedure,processing instruction,property,record,schema,ssh,template,templating language,terminal,toxic,user defined function
Platform: UNKNOWN
Classifier: Development Status :: 5 - Production/Stable
Classifier: Environment :: No Input/Output (Daemon)
Classifier: Environment :: Web Environment
Classifier: Intended Audience :: Developers
Classifier: License :: OSI Approved :: MIT License
Classifier: Operating System :: OS Independent
Classifier: Operating System :: POSIX
Classifier: Programming Language :: Python
Classifier: Programming Language :: Python :: 3
Classifier: Programming Language :: Python :: 3 :: Only
Classifier: Programming Language :: Python :: 3.10
Classifier: Programming Language :: Python :: 3.11
Classifier: Programming Language :: Python :: 3.12
Classifier: Topic :: Database
Classifier: Topic :: Internet
Classifier: Topic :: Internet :: File Transfer Protocol (FTP)
Classifier: Topic :: Internet :: WWW/HTTP
Classifier: Topic :: Internet :: WWW/HTTP :: Dynamic Content
Classifier: Topic :: Internet :: WWW/HTTP :: Site Management
Classifier: Topic :: Multimedia :: Graphics
Classifier: Topic :: Software Development :: Build Tools
Classifier: Topic :: Software Development :: Libraries :: Python Modules
Classifier: Topic :: Terminals
Classifier: Topic :: Text Processing :: General
Classifier: Topic :: Text Processing :: Markup :: HTML
Classifier: Topic :: Text Processing :: Markup :: XML
Requires-Python: >=3.10
Requires-Dist: cssutils >=2.6.0
Provides-Extra: html
Requires-Dist: lxml >=4.3.4 ; extra == 'html'
Provides-Extra: oracle
Requires-Dist: oracledb >=2.5.0 ; extra == 'oracle'
Provides-Extra: postgres
Requires-Dist: psycopg[binary] >=3.0.5 ; extra == 'postgres'
Provides-Extra: proctitle
Requires-Dist: setproctitle >=1.1.8 ; extra == 'proctitle'
Provides-Extra: requests
Requires-Dist: requests >=2.22.0 ; extra == 'requests'
